pyshtools.libs/libquadmath-96973f99.so.0.0.0
pyshtools.libs/libgfortran-040039e1.so.5.0.0
pyshtools.libs/libopenblasp-r0-35c2a7de.3.21.so
pyshtools/_SHTOOLS.cpython-311-x86_64-linux-gnu.so
pyshtools/__init__.py
pyshtools/shio/__init__.py
pyshtools/shio/yilm_index_vector.py
pyshtools/shio/bshc.py
pyshtools/shio/shtools.py
pyshtools/shio/convert.py
pyshtools/shio/read_igrf.py
pyshtools/shio/dov.py
pyshtools/shio/icgem.py
pyshtools/spectralanalysis/__init__.py
pyshtools/spectralanalysis/cross_spectrum.py
pyshtools/spectralanalysis/spectrum.py
pyshtools/expand/__init__.py
pyshtools/expand/spharm_functions.py
pyshtools/doc/glqgridcoord.doc
pyshtools/doc/shreturntapers.doc
pyshtools/doc/shmtcouplingmatrix.doc
pyshtools/doc/djpi2.doc
pyshtools/doc/shrtoc.doc
pyshtools/doc/cilmminusrhohdh.doc
pyshtools/doc/plbar_d1.doc
pyshtools/doc/normalgravity.doc
pyshtools/doc/plegendre_d1.doc
pyshtools/doc/plbar.doc
pyshtools/doc/makegravgradgriddh.doc
pyshtools/doc/shcilmtovector.doc
pyshtools/doc/shfindlwin.doc
pyshtools/doc/makegridglq.doc
pyshtools/doc/plon.doc
pyshtools/doc/shrotaterealcoef.doc
pyshtools/doc/shbiasadmitcorr.doc
pyshtools/doc/dhaj.doc
pyshtools/doc/shmtvar.doc
pyshtools/doc/shmultitapercse.doc
pyshtools/doc/slepiancoeffs.doc
pyshtools/doc/shexpandglq.doc
pyshtools/doc/shcindextocilm.doc
pyshtools/doc/yilmindexvector.doc
pyshtools/doc/shmtdebias.doc
pyshtools/doc/shread2.doc
pyshtools/doc/cilmplusrhohdh.doc
pyshtools/doc/shexpandwlsq.doc
pyshtools/doc/batohilmrhohdh.doc
pyshtools/doc/wigner3j.doc
pyshtools/doc/shexpanddhc.doc
pyshtools/doc/makeellipsecoord.doc
pyshtools/doc/plegendre.doc
pyshtools/doc/plmindex.doc
pyshtools/doc/plmon.doc
pyshtools/doc/makegeoidgriddh.doc
pyshtools/doc/computedg82.doc
pyshtools/doc/shconfidence.doc
pyshtools/doc/shexpanddh.doc
pyshtools/doc/computedm.doc
pyshtools/doc/shrotatetapers.doc
pyshtools/doc/makegriddh.doc
pyshtools/doc/shcilmtocindex.doc
pyshtools-4.12.2.dist-info/RECORD
pyshtools-4.12.2.dist-info/METADATA
pyshtools-4.12.2.dist-info/WHEEL
