Metadata-Version: 2.1
Name: pyshtools
Version: 4.12.2
Summary: SHTOOLS - Spherical Harmonic Tools
Keywords: Spherical Harmonics Spectral Estimation Slepian Functions Legendre Functions Gravity Field Magnetic Field
Home-page: https://shtools.github.io/SHTOOLS/
Author-Email: The SHTOOLS developers <mark.wieczorek@ipgp.fr>
License: BSD-3-Clause
Classifier: Development Status :: 5 - Production/Stable
Classifier: Environment :: Console
Classifier: Intended Audience :: Science/Research
Classifier: Intended Audience :: Developers
Classifier: License :: OSI Approved :: BSD License
Classifier: Natural Language :: English
Classifier: Operating System :: OS Independent
Classifier: Programming Language :: Fortran
Classifier: Programming Language :: Python
Classifier: Programming Language :: Python :: 3
Classifier: Topic :: Scientific/Engineering
Classifier: Topic :: Scientific/Engineering :: GIS
Classifier: Topic :: Scientific/Engineering :: Mathematics
Classifier: Topic :: Scientific/Engineering :: Physics
Project-URL: Homepage, https://shtools.github.io/SHTOOLS/
Project-URL: Download, https://github.com/SHTOOLS/SHTOOLS/zipball/master
Requires-Python: >=3.9
Requires-Dist: numpy
Requires-Dist: scipy>=0.14.0
Requires-Dist: matplotlib>=3.3
Requires-Dist: astropy>=4.0
Requires-Dist: xarray
Requires-Dist: requests
Requires-Dist: pooch>=1.1
Requires-Dist: tqdm
Requires-Dist: cartopy>=0.18.0; extra == "cartopy"
Requires-Dist: pygmt>=0.7; extra == "pygmt"
Requires-Dist: palettable>=3.3; extra == "palettable"
Requires-Dist: ducc0>=0.15; extra == "ducc"
Provides-Extra: cartopy
Provides-Extra: pygmt
Provides-Extra: palettable
Provides-Extra: ducc
